MANIFEST.in
README.rst
setup.py
docs/HISTORY.rst
docs/INSTALL.txt
docs/LICENSE.GPL
docs/LICENSE.txt
ospfe/__init__.py
ospfe.occhiello.egg-info/PKG-INFO
ospfe.occhiello.egg-info/SOURCES.txt
ospfe.occhiello.egg-info/dependency_links.txt
ospfe.occhiello.egg-info/entry_points.txt
ospfe.occhiello.egg-info/namespace_packages.txt
ospfe.occhiello.egg-info/not-zip-safe
ospfe.occhiello.egg-info/requires.txt
ospfe.occhiello.egg-info/top_level.txt
ospfe/occhiello/__init__.py
ospfe/occhiello/configure.zcml
ospfe/occhiello/extender.py
ospfe/occhiello/interfaces.py
ospfe/occhiello/testing.py
ospfe/occhiello/Extensions/install.py
ospfe/occhiello/browser/O.png
ospfe/occhiello/browser/__init__.py
ospfe/occhiello/browser/configure.zcml
ospfe/occhiello/browser/controlpanel.py
ospfe/occhiello/browser/occhiello.css
ospfe/occhiello/browser/occhiello.pt
ospfe/occhiello/browser/occhiello.py
ospfe/occhiello/locales/ospfe.occhiello-manual.pot
ospfe/occhiello/locales/ospfe.occhiello.pot
ospfe/occhiello/locales/rebuildPo.sh
ospfe/occhiello/locales/it/LC_MESSAGES/ospfe.occhiello.mo
ospfe/occhiello/locales/it/LC_MESSAGES/ospfe.occhiello.po
ospfe/occhiello/profiles/default/browserlayer.xml
ospfe/occhiello/profiles/default/controlpanel.xml
ospfe/occhiello/profiles/default/cssregistry.xml
ospfe/occhiello/profiles/default/metadata.xml
ospfe/occhiello/profiles/default/registry.xml
ospfe/occhiello/profiles/default/rolemap.xml
ospfe/occhiello/profiles/uninstall/browserlayer.xml
ospfe/occhiello/profiles/uninstall/controlpanel.xml
ospfe/occhiello/profiles/uninstall/cssregistry.xml
ospfe/occhiello/profiles/uninstall/registry.xml
ospfe/occhiello/tests/__init__.py
ospfe/occhiello/tests/test_viewlet.py