Metadata-Version: 1.0
Name: ospfe.occhiello
Version: 2.0.1
Summary: Add a new Plone introduction field (half-title), displayed before document title
Home-page: https://github.com/RedTurtle/ospfe.occhiello
Author: RedTurtle Technology
Author-email: sviluppoplone@redturtle.it
License: GPL
Keywords: plone title field plonegov half-title
Platform: UNKNOWN
Classifier: Development Status :: 4 - Beta
Classifier: Framework :: Plone
Classifier: Framework :: Plone :: 4.2
Classifier: Framework :: Plone :: 4.3
Classifier: Programming Language :: Python
